{
  "version": "2.6.0",
  "summary": {
    "title": "Sitio web de la biblioteca universitaria",
    "owner": "alberto0141",
    "description": "El sitio web de la biblioteca universitaria es la primera implementación de un \nsitio web para brindar servicios en línea a los bibliotecarios y usuarios de la biblioteca \n(estudiantes y personal universitario). Como esta es la primera implementación del sitio \nweb, la funcionalidad será limitada. Serán tres usuarios de la aplicación: \n1. Estudiantes \n2. Personal \n3. Bibliotecarios \nEl personal y los estudiantes podrán iniciar sesión y buscar libros, y los miembros del \npersonal podrán solicitar libros. Los bibliotecarios podrán iniciar sesión, agregar libros, \nagregar usuarios y buscar libros.",
    "id": 0
  },
  "detail": {
    "contributors": [],
    "diagrams": [
      {
        "id": 0,
        "title": "Nuevo diagrama STRIDE",
        "diagramType": "STRIDE",
        "placeholder": "Descripción de nuevo diagrama STRIDE",
        "thumbnail": "./public/content/images/thumbnail.stride.jpg",
        "version": "2.6.0",
        "cells": [
          {
            "position": {
              "x": 120,
              "y": 130
            },
            "size": {
              "width": 112.5,
              "height": 60
            },
            "attrs": {
              "text": {
                "text": "Bibliotecario"
              },
              "body": {
                "stroke": "red",
                "strokeWidth": 2.5,
                "strokeDasharray": null
              }
            },
            "visible": true,
            "shape": "actor",
            "zIndex": 1,
            "ports": {
              "groups": {
                "top": {
                  "position": "top",
                  "attrs": {
                    "circle": {
                      "r": 4,
                      "magnet": true,
                      "stroke": "#5F95FF",
                      "strokeWidth": 1,
                      "fill": "#fff",
                      "style": {
                        "visibility": "hidden"
                      }
                    }
                  }
                },
                "right": {
                  "position": "right",
                  "attrs": {
                    "circle": {
                      "r": 4,
                      "magnet": true,
                      "stroke": "#5F95FF",
                      "strokeWidth": 1,
                      "fill": "#fff",
                      "style": {
                        "visibility": "hidden"
                      }
                    }
                  }
                },
                "bottom": {
                  "position": "bottom",
                  "attrs": {
                    "circle": {
                      "r": 4,
                      "magnet": true,
                      "stroke": "#5F95FF",
                      "strokeWidth": 1,
                      "fill": "#fff",
                      "style": {
                        "visibility": "hidden"
                      }
                    }
                  }
                },
                "left": {
                  "position": "left",
                  "attrs": {
                    "circle": {
                      "r": 4,
                      "magnet": true,
                      "stroke": "#5F95FF",
                      "strokeWidth": 1,
                      "fill": "#fff",
                      "style": {
                        "visibility": "hidden"
                      }
                    }
                  }
                }
              },
              "items": [
                {
                  "group": "top",
                  "id": "745f7ba6-ebf8-456d-a6a8-b30c3ee75239"
                },
                {
                  "group": "right",
                  "id": "6b175791-f2c3-460e-9256-a445f97050d2"
                },
                {
                  "group": "bottom",
                  "id": "e038b66a-bf27-4c12-8413-76ebc4b0cc4f"
                },
                {
                  "group": "left",
                  "id": "2f5919b5-efd2-4a87-ab6a-b76d2523d8d6"
                }
              ]
            },
            "id": "cb82aad2-43ff-4fd8-bce4-5c1196bf3e67",
            "data": {
              "type": "tm.Actor",
              "name": "Bibliotecario",
              "description": "(4) Bibliotecario.",
              "isTrustBoundary": false,
              "outOfScope": false,
              "reasonOutOfScope": "",
              "hasOpenThreats": true,
              "providesAuthentication": false,
              "threats": [
                {
                  "id": "5d06d830-07a4-406b-9a2c-1b3be18dfd7e",
                  "title": "Falsificación  de identidad ",
                  "status": "Open",
                  "severity": "Low",
                  "type": "Spoofing / Spoofing",
                  "description": "Acción de amenaza destinada \na acceder y utilizar las \ncredenciales de otro usuario, \ncomo el nombre de usuario y \nla contraseña. ",
                  "mitigation": "1. Autenticación \nadecuada \n2. Proteger datos secretos \n3. No almacenar secretos ",
                  "modelType": "STRIDE",
                  "new": false,
                  "number": 2,
                  "score": "1"
                }
              ],
              "threatFrequency": {
                "spoofing": 1,
                "repudiation": 0
              }
            }
          },
          {
            "position": {
              "x": 120,
              "y": 4
            },
            "size": {
              "width": 110,
              "height": 60
            },
            "attrs": {
              "text": {
                "text": "Usuario"
              },
              "body": {
                "stroke": "red",
                "strokeWidth": 2.5,
                "strokeDasharray": null
              }
            },
            "visible": true,
            "shape": "actor",
            "zIndex": 2,
            "ports": {
              "groups": {
                "top": {
                  "position": "top",
                  "attrs": {
                    "circle": {
                      "r": 4,
                      "magnet": true,
                      "stroke": "#5F95FF",
                      "strokeWidth": 1,
                      "fill": "#fff",
                      "style": {
                        "visibility": "hidden"
                      }
                    }
                  }
                },
                "right": {
                  "position": "right",
                  "attrs": {
                    "circle": {
                      "r": 4,
                      "magnet": true,
                      "stroke": "#5F95FF",
                      "strokeWidth": 1,
                      "fill": "#fff",
                      "style": {
                        "visibility": "hidden"
                      }
                    }
                  }
                },
                "bottom": {
                  "position": "bottom",
                  "attrs": {
                    "circle": {
                      "r": 4,
                      "magnet": true,
                      "stroke": "#5F95FF",
                      "strokeWidth": 1,
                      "fill": "#fff",
                      "style": {
                        "visibility": "hidden"
                      }
                    }
                  }
                },
                "left": {
                  "position": "left",
                  "attrs": {
                    "circle": {
                      "r": 4,
                      "magnet": true,
                      "stroke": "#5F95FF",
                      "strokeWidth": 1,
                      "fill": "#fff",
                      "style": {
                        "visibility": "hidden"
                      }
                    }
                  }
                }
              },
              "items": [
                {
                  "group": "top",
                  "id": "745f7ba6-ebf8-456d-a6a8-b30c3ee75239"
                },
                {
                  "group": "right",
                  "id": "6b175791-f2c3-460e-9256-a445f97050d2"
                },
                {
                  "group": "bottom",
                  "id": "e038b66a-bf27-4c12-8413-76ebc4b0cc4f"
                },
                {
                  "group": "left",
                  "id": "2f5919b5-efd2-4a87-ab6a-b76d2523d8d6"
                }
              ]
            },
            "id": "0c389a7f-2134-415d-80b5-0fd8e6dee929",
            "data": {
              "type": "tm.Actor",
              "name": "Usuario",
              "description": "(1) Usuario web anónimo. \n(2) Usuario con credenciales de \ninicio de sesión válidas. \n(3) Usuario con credenciales de \ninicio de sesión no válidas. ",
              "isTrustBoundary": false,
              "outOfScope": false,
              "reasonOutOfScope": "",
              "hasOpenThreats": true,
              "providesAuthentication": false,
              "threats": [
                {
                  "id": "65687354-02dd-449f-8eb8-d7cf1cefab79",
                  "title": "Falsificación  de identidad ",
                  "status": "Open",
                  "severity": "Low",
                  "type": "Spoofing / Spoofing",
                  "description": "Acción de amenaza destinada \na acceder y utilizar las \ncredenciales de otro usuario, \ncomo el nombre de usuario y \nla contraseña. ",
                  "mitigation": "1. Autenticación \nadecuada \n2. Proteger datos secretos \n3. No almacenar secretos ",
                  "modelType": "STRIDE",
                  "new": false,
                  "number": 1,
                  "score": "1"
                }
              ],
              "threatFrequency": {
                "spoofing": 1,
                "repudiation": 0
              }
            }
          },
          {
            "position": {
              "x": 380,
              "y": 70
            },
            "size": {
              "width": 60,
              "height": 60
            },
            "attrs": {
              "text": {
                "text": "Sitio web biblioteca"
              },
              "body": {
                "stroke": "red",
                "strokeWidth": 2.5,
                "strokeDasharray": null
              }
            },
            "visible": true,
            "shape": "process",
            "zIndex": 3,
            "ports": {
              "groups": {
                "top": {
                  "position": "top",
                  "attrs": {
                    "circle": {
                      "r": 4,
                      "magnet": true,
                      "stroke": "#5F95FF",
                      "strokeWidth": 1,
                      "fill": "#fff",
                      "style": {
                        "visibility": "hidden"
                      }
                    }
                  }
                },
                "right": {
                  "position": "right",
                  "attrs": {
                    "circle": {
                      "r": 4,
                      "magnet": true,
                      "stroke": "#5F95FF",
                      "strokeWidth": 1,
                      "fill": "#fff",
                      "style": {
                        "visibility": "hidden"
                      }
                    }
                  }
                },
                "bottom": {
                  "position": "bottom",
                  "attrs": {
                    "circle": {
                      "r": 4,
                      "magnet": true,
                      "stroke": "#5F95FF",
                      "strokeWidth": 1,
                      "fill": "#fff",
                      "style": {
                        "visibility": "hidden"
                      }
                    }
                  }
                },
                "left": {
                  "position": "left",
                  "attrs": {
                    "circle": {
                      "r": 4,
                      "magnet": true,
                      "stroke": "#5F95FF",
                      "strokeWidth": 1,
                      "fill": "#fff",
                      "style": {
                        "visibility": "hidden"
                      }
                    }
                  }
                }
              },
              "items": [
                {
                  "group": "top",
                  "id": "42c734f2-6ea4-45ec-ad23-7064fee88bdb"
                },
                {
                  "group": "right",
                  "id": "a553cedf-2a94-4bee-af51-c82924978c93"
                },
                {
                  "group": "bottom",
                  "id": "85ae76c4-ed84-42ac-8b1c-dba0517ebc9f"
                },
                {
                  "group": "left",
                  "id": "d0a4f9f0-50d4-4b0f-b44b-a20e1e5eaf2c"
                }
              ]
            },
            "id": "82bc7ef6-4340-4c03-a303-e6c374f082b3",
            "data": {
              "type": "tm.Process",
              "name": "Sitio web biblioteca",
              "description": "El sitio web de la biblioteca \nuniversitaria se ejecutará en un \nservidor Linux con Apache. Este \nservidor será reforzado según el \nestándar de protección de servidores \nde la universidad.",
              "outOfScope": false,
              "isTrustBoundary": false,
              "reasonOutOfScope": "",
              "hasOpenThreats": true,
              "handlesCardPayment": false,
              "handlesGoodsOrServices": false,
              "isWebApplication": false,
              "privilegeLevel": "",
              "threats": [
                {
                  "id": "645568eb-b19a-4606-a6bd-3c205e8a7c77",
                  "title": "Negación de  servicio ",
                  "status": "Open",
                  "severity": "Medium",
                  "type": "Denial of service / Denegación de servicio",
                  "description": "Un atacante podría denegar el \nacceso a usuarios válidos, \nhaciendo que el servidor web \nno esté disponible o sea \ninutilizable temporalmente \npor medio del envío de \nmúltiples peticiones \nsimultaneas.",
                  "mitigation": "Se utiliza un balanceo de \ncargas en el servidor web. \nSe monitorean las \ndirecciones IP de los \nclientes y al encontrar un \nposible ataque, se bloquea \nel acceso. \nSe considera contratar un \nservicio de VPN para \nocultar la dirección IP \npública a los clientes. \n \nEsta en desarrollo el \nbalanceo de cargas. \nParcialmente mitigada. ",
                  "modelType": "STRIDE",
                  "new": false,
                  "number": 3,
                  "score": "2"
                }
              ],
              "threatFrequency": {
                "spoofing": 0,
                "tampering": 0,
                "repudiation": 0,
                "informationDisclosure": 0,
                "denialOfService": 1,
                "elevationOfPrivilege": 0
              }
            }
          },
          {
            "shape": "flow",
            "attrs": {
              "line": {
                "stroke": "red",
                "strokeWidth": 2.5,
                "targetMarker": {
                  "name": "block"
                },
                "sourceMarker": {
                  "name": ""
                },
                "strokeDasharray": null
              }
            },
            "width": 200,
            "height": 100,
            "zIndex": 10,
            "connector": "smooth",
            "data": {
              "type": "tm.Flow",
              "name": "Web request",
              "description": "Respuestas recibidas de la aplicacion por parte de los usuarios",
              "outOfScope": false,
              "isTrustBoundary": false,
              "reasonOutOfScope": "",
              "hasOpenThreats": true,
              "isBidirectional": false,
              "isEncrypted": false,
              "isPublicNetwork": false,
              "protocol": "",
              "threats": [
                {
                  "id": "993bb30d-1752-405d-ae52-ac84a5050639",
                  "title": "Divulgacion de informacion",
                  "status": "Open",
                  "severity": "High",
                  "type": "Information disclosure",
                  "description": "estas solicitudes se transmiten a través de la internet publica y podrían ser interceptadas por un atacante",
                  "mitigation": "las solicitudes deberían requerir HTTPS/S. Esto proporcionara confidencialidad e integridad. HTTP no debe ser compatible.",
                  "modelType": "STRIDE",
                  "new": false,
                  "number": 4,
                  "score": ""
                }
              ],
              "trustBoundaryIds": [],
              "threatFrequency": {
                "tampering": 0,
                "informationDisclosure": 1,
                "denialOfService": 0
              }
            },
            "labels": [
              "Web request"
            ],
            "id": "1b423fc8-4130-48ff-849d-aa0fc693b121",
            "source": {
              "cell": "0c389a7f-2134-415d-80b5-0fd8e6dee929",
              "port": "6b175791-f2c3-460e-9256-a445f97050d2"
            },
            "target": {
              "cell": "82bc7ef6-4340-4c03-a303-e6c374f082b3",
              "port": "d0a4f9f0-50d4-4b0f-b44b-a20e1e5eaf2c"
            },
            "vertices": [
              {
                "x": 250,
                "y": -50
              }
            ]
          },
          {
            "shape": "flow",
            "attrs": {
              "line": {
                "stroke": "red",
                "strokeWidth": 2.5,
                "targetMarker": {
                  "name": "block"
                },
                "sourceMarker": {
                  "name": ""
                },
                "strokeDasharray": null
              }
            },
            "width": 200,
            "height": 100,
            "zIndex": 10,
            "connector": "smooth",
            "data": {
              "type": "tm.Flow",
              "name": "Web Response",
              "description": "Respuestas enviadas por la aplicacion hacia los usuarios",
              "outOfScope": false,
              "isTrustBoundary": false,
              "reasonOutOfScope": "",
              "hasOpenThreats": true,
              "isBidirectional": false,
              "isEncrypted": false,
              "isPublicNetwork": false,
              "protocol": "",
              "threats": [
                {
                  "id": "0b5f486c-e986-4308-9383-b319135fbfab",
                  "title": "Divulgacion de informcion",
                  "status": "Open",
                  "severity": "High",
                  "type": "Tampering",
                  "description": "Estas respustas se transmiten a traves de la internet publica y podrian ser interceptaadas por un atacante",
                  "mitigation": "Las respuestas deberian requerir HTTPS/S. esto proporcionara confidencialidad e integrgidad. HTTP no debe ser compatible",
                  "modelType": "STRIDE",
                  "new": false,
                  "number": 5,
                  "score": ""
                }
              ],
              "trustBoundaryIds": [],
              "threatFrequency": {
                "tampering": 1,
                "informationDisclosure": 0,
                "denialOfService": 0
              }
            },
            "labels": [
              "Web Response"
            ],
            "id": "9395ef08-456d-4fcc-bba2-700cc524c59c",
            "source": {
              "cell": "82bc7ef6-4340-4c03-a303-e6c374f082b3",
              "port": "d0a4f9f0-50d4-4b0f-b44b-a20e1e5eaf2c"
            },
            "target": {
              "cell": "0c389a7f-2134-415d-80b5-0fd8e6dee929",
              "port": "6b175791-f2c3-460e-9256-a445f97050d2"
            },
            "vertices": [
              {
                "x": 290,
                "y": 34
              }
            ]
          },
          {
            "shape": "flow",
            "attrs": {
              "line": {
                "stroke": "red",
                "strokeWidth": 2.5,
                "targetMarker": {
                  "name": "block"
                },
                "sourceMarker": {
                  "name": ""
                },
                "strokeDasharray": null
              }
            },
            "width": 200,
            "height": 100,
            "zIndex": 10,
            "connector": "smooth",
            "data": {
              "type": "tm.Flow",
              "name": "Web request",
              "description": "Respuestas recibidas por la aplicacion de los bibliotecarios",
              "outOfScope": false,
              "isTrustBoundary": false,
              "reasonOutOfScope": "",
              "hasOpenThreats": true,
              "isBidirectional": false,
              "isEncrypted": false,
              "isPublicNetwork": false,
              "protocol": "",
              "threats": [
                {
                  "id": "151f6f1d-2ea5-4bed-be57-88842660abbf",
                  "title": "El flujo de datos debe utilizar HTTP/S",
                  "status": "Open",
                  "severity": "High",
                  "type": "Information disclosure",
                  "description": "Estas solicitudes se transmiten a traves de la internet publica y podrian ser interceptadas por un atacante.",
                  "mitigation": "las solicitudes deberias requerir HTTPS/S. Esto proporcionara confidencialidad e integridad.hTTP no debe ser compatible",
                  "modelType": "STRIDE",
                  "new": false,
                  "number": 6,
                  "score": ""
                }
              ],
              "trustBoundaryIds": [],
              "threatFrequency": {
                "tampering": 0,
                "informationDisclosure": 1,
                "denialOfService": 0
              }
            },
            "labels": [
              "Web request"
            ],
            "id": "85ac052d-e752-44ca-b8e1-ef8a94395380",
            "source": {
              "cell": "cb82aad2-43ff-4fd8-bce4-5c1196bf3e67",
              "port": "6b175791-f2c3-460e-9256-a445f97050d2"
            },
            "target": {
              "cell": "82bc7ef6-4340-4c03-a303-e6c374f082b3",
              "port": "d0a4f9f0-50d4-4b0f-b44b-a20e1e5eaf2c"
            },
            "vertices": []
          },
          {
            "shape": "flow",
            "attrs": {
              "line": {
                "stroke": "red",
                "strokeWidth": 2.5,
                "targetMarker": {
                  "name": "block"
                },
                "sourceMarker": {
                  "name": ""
                },
                "strokeDasharray": null
              }
            },
            "width": 200,
            "height": 100,
            "zIndex": 10,
            "connector": "smooth",
            "data": {
              "type": "tm.Flow",
              "name": "Web response",
              "description": "Respuestas enviadas por la aplicación hacia los bibliotecarios.",
              "outOfScope": false,
              "isTrustBoundary": false,
              "reasonOutOfScope": "",
              "hasOpenThreats": true,
              "isBidirectional": false,
              "isEncrypted": false,
              "isPublicNetwork": false,
              "protocol": "",
              "threats": [
                {
                  "id": "cf68e3b2-ad38-4816-9cdb-6734912f049a",
                  "title": "el flujo de datos debe utilizar HTTP/S",
                  "status": "Open",
                  "severity": "High",
                  "type": "Information disclosure",
                  "description": "Estas respuestas se transmiten a través de internet publica y podrían ser interceptadas por un atacante",
                  "mitigation": "las respuestas deben requerir HTTPS/S. esto proporcionara confidencialidad e integridad. HTTP no debe ser compatible",
                  "modelType": "STRIDE",
                  "new": false,
                  "number": 7,
                  "score": ""
                }
              ],
              "trustBoundaryIds": [],
              "threatFrequency": {
                "tampering": 0,
                "informationDisclosure": 1,
                "denialOfService": 0
              }
            },
            "labels": [
              "Web response"
            ],
            "id": "5bc67659-fe91-433c-b98e-ae3f1ba08249",
            "source": {
              "cell": "82bc7ef6-4340-4c03-a303-e6c374f082b3",
              "port": "d0a4f9f0-50d4-4b0f-b44b-a20e1e5eaf2c"
            },
            "target": {
              "cell": "cb82aad2-43ff-4fd8-bce4-5c1196bf3e67",
              "port": "6b175791-f2c3-460e-9256-a445f97050d2"
            },
            "vertices": [
              {
                "x": 260,
                "y": 230
              }
            ]
          },
          {
            "shape": "flow",
            "attrs": {
              "line": {
                "stroke": "#333333",
                "targetMarker": {
                  "name": "block"
                },
                "sourceMarker": {
                  "name": ""
                },
                "strokeDasharray": null
              }
            },
            "width": 200,
            "height": 100,
            "zIndex": 10,
            "connector": "smooth",
            "data": {
              "type": "tm.Flow",
              "name": "Queries",
              "description": "instruccion sql enviadas a la base de datos",
              "outOfScope": false,
              "isTrustBoundary": false,
              "reasonOutOfScope": "",
              "hasOpenThreats": false,
              "isBidirectional": false,
              "isEncrypted": false,
              "isPublicNetwork": false,
              "protocol": "",
              "threats": [
                {
                  "id": "426ab391-be52-4faa-b033-4c4db15dfb04",
                  "title": "Ataque man in the middle",
                  "status": "Mitigated",
                  "severity": "Low",
                  "type": "Information disclosure",
                  "description": "un atacnte podria interceptar las consultas de la base de datos en transito y  obtener informaacion confidencial, como credenciales de la base de datos, parametros de consulta o resultados de la consulta (es poco probable ya que el flujo de la base de datos se realiza a traves de una red privada).",
                  "mitigation": "aplicar una conexion cifrada en el servidor de la bd",
                  "modelType": "STRIDE",
                  "new": false,
                  "number": 9,
                  "score": ""
                }
              ],
              "trustBoundaryIds": [],
              "threatFrequency": {
                "tampering": 0,
                "informationDisclosure": 1,
                "denialOfService": 0
              }
            },
            "labels": [
              "Queries"
            ],
            "id": "2de3ee8f-e1a7-4264-86a9-0afe43ee76d7",
            "source": {
              "cell": "82bc7ef6-4340-4c03-a303-e6c374f082b3",
              "port": "a553cedf-2a94-4bee-af51-c82924978c93"
            },
            "target": {
              "cell": "afa88889-f448-4b87-b2d7-c32a30e0b31b",
              "port": "14018021-cdd3-4b69-9d20-d80402cecd02"
            },
            "vertices": [
              {
                "x": 490,
                "y": 140
              }
            ]
          },
          {
            "shape": "flow",
            "attrs": {
              "line": {
                "stroke": "#333333",
                "targetMarker": {
                  "name": "block"
                },
                "sourceMarker": {
                  "name": ""
                },
                "strokeDasharray": null
              }
            },
            "width": 200,
            "height": 100,
            "zIndex": 10,
            "connector": "smooth",
            "data": {
              "type": "tm.Flow",
              "name": "Resultados web app query",
              "description": "datos recuperados desde la base de datos.",
              "outOfScope": false,
              "isTrustBoundary": false,
              "reasonOutOfScope": "",
              "hasOpenThreats": false,
              "isBidirectional": false,
              "isEncrypted": false,
              "isPublicNetwork": false,
              "protocol": "",
              "threats": [
                {
                  "id": "cf8d0c64-1e5a-4451-9dc8-dc5472d5a338",
                  "title": "ataque man in the midle",
                  "status": "Mitigated",
                  "severity": "Low",
                  "type": "Information disclosure",
                  "description": "un atacante podría interceptar las consultas de la base de datos en tránsito y obtener información confidencial, como credenciales de la base de datos, parámetros de consulta o resultados de la consulta (es poco probable ya que el flujo de datos se realiza a través de una red privada",
                  "mitigation": "aplicar una conexión cifrada al servidor de la base de datos",
                  "modelType": "STRIDE",
                  "new": false,
                  "number": 10,
                  "score": "1"
                }
              ],
              "trustBoundaryIds": [],
              "threatFrequency": {
                "tampering": 0,
                "informationDisclosure": 1,
                "denialOfService": 0
              }
            },
            "labels": [
              "Resultados web app query"
            ],
            "id": "9df9ac98-dee0-4f98-b3f6-d99bfaa2c362",
            "source": {
              "cell": "afa88889-f448-4b87-b2d7-c32a30e0b31b",
              "port": "14018021-cdd3-4b69-9d20-d80402cecd02"
            },
            "target": {
              "cell": "82bc7ef6-4340-4c03-a303-e6c374f082b3",
              "port": "a553cedf-2a94-4bee-af51-c82924978c93"
            },
            "vertices": [
              {
                "x": 570,
                "y": 80
              }
            ]
          },
          {
            "position": {
              "x": 340,
              "y": 280
            },
            "size": {
              "width": 120,
              "height": 60
            },
            "attrs": {
              "text": {
                "text": "Paginas"
              },
              "topLine": {
                "strokeWidth": 1.5,
                "strokeDasharray": null
              },
              "bottomLine": {
                "strokeWidth": 1.5,
                "strokeDasharray": null
              }
            },
            "visible": true,
            "shape": "store",
            "ports": {
              "groups": {
                "top": {
                  "position": "top",
                  "attrs": {
                    "circle": {
                      "r": 4,
                      "magnet": true,
                      "stroke": "#5F95FF",
                      "strokeWidth": 1,
                      "fill": "#fff",
                      "style": {
                        "visibility": "hidden"
                      }
                    }
                  }
                },
                "right": {
                  "position": "right",
                  "attrs": {
                    "circle": {
                      "r": 4,
                      "magnet": true,
                      "stroke": "#5F95FF",
                      "strokeWidth": 1,
                      "fill": "#fff",
                      "style": {
                        "visibility": "hidden"
                      }
                    }
                  }
                },
                "bottom": {
                  "position": "bottom",
                  "attrs": {
                    "circle": {
                      "r": 4,
                      "magnet": true,
                      "stroke": "#5F95FF",
                      "strokeWidth": 1,
                      "fill": "#fff",
                      "style": {
                        "visibility": "hidden"
                      }
                    }
                  }
                },
                "left": {
                  "position": "left",
                  "attrs": {
                    "circle": {
                      "r": 4,
                      "magnet": true,
                      "stroke": "#5F95FF",
                      "strokeWidth": 1,
                      "fill": "#fff",
                      "style": {
                        "visibility": "hidden"
                      }
                    }
                  }
                }
              },
              "items": [
                {
                  "group": "top",
                  "id": "14018021-cdd3-4b69-9d20-d80402cecd02"
                },
                {
                  "group": "right",
                  "id": "d3a25149-5a7f-44aa-922f-b324230f6ec8"
                },
                {
                  "group": "bottom",
                  "id": "9f9c2a49-44b1-4192-8aee-b60fe5e1523b"
                },
                {
                  "group": "left",
                  "id": "36f7dcb0-9ee8-4527-b10f-85725745f27f"
                }
              ]
            },
            "id": "29d57360-5d33-4d13-8bf0-edff55998347",
            "zIndex": 11,
            "data": {
              "type": "tm.Store",
              "name": "Paginas",
              "description": "Páginas web leídas desde el disco",
              "outOfScope": false,
              "isTrustBoundary": false,
              "reasonOutOfScope": "",
              "hasOpenThreats": false,
              "isALog": false,
              "isEncrypted": false,
              "isSigned": false,
              "storesCredentials": false,
              "storesInventory": false,
              "threats": [
                {
                  "id": "b341bc5a-ed6d-4544-a95b-f33ce6e9d06e",
                  "title": "Modificacion sin autorizacion (Tampering)",
                  "status": "Mitigated",
                  "severity": "High",
                  "type": "Tampering",
                  "description": "Un atacante podria modificar las paginas web sin autorizacion",
                  "mitigation": "las paginas solo tienen acceso a lectura. unicamente el usuario administrador puede tener acceso de escritura.",
                  "modelType": "STRIDE",
                  "new": false,
                  "number": 11,
                  "score": "1"
                }
              ],
              "threatFrequency": {
                "tampering": 1,
                "repudiation": 0,
                "informationDisclosure": 0,
                "denialOfService": 0
              }
            }
          },
          {
            "position": {
              "x": 550,
              "y": 170
            },
            "size": {
              "width": 120,
              "height": 60
            },
            "attrs": {
              "text": {
                "text": "Lee web app config"
              },
              "topLine": {
                "strokeWidth": 1.5,
                "strokeDasharray": null
              },
              "bottomLine": {
                "strokeWidth": 1.5,
                "strokeDasharray": null
              }
            },
            "visible": true,
            "shape": "store",
            "ports": {
              "groups": {
                "top": {
                  "position": "top",
                  "attrs": {
                    "circle": {
                      "r": 4,
                      "magnet": true,
                      "stroke": "#5F95FF",
                      "strokeWidth": 1,
                      "fill": "#fff",
                      "style": {
                        "visibility": "hidden"
                      }
                    }
                  }
                },
                "right": {
                  "position": "right",
                  "attrs": {
                    "circle": {
                      "r": 4,
                      "magnet": true,
                      "stroke": "#5F95FF",
                      "strokeWidth": 1,
                      "fill": "#fff",
                      "style": {
                        "visibility": "hidden"
                      }
                    }
                  }
                },
                "bottom": {
                  "position": "bottom",
                  "attrs": {
                    "circle": {
                      "r": 4,
                      "magnet": true,
                      "stroke": "#5F95FF",
                      "strokeWidth": 1,
                      "fill": "#fff",
                      "style": {
                        "visibility": "hidden"
                      }
                    }
                  }
                },
                "left": {
                  "position": "left",
                  "attrs": {
                    "circle": {
                      "r": 4,
                      "magnet": true,
                      "stroke": "#5F95FF",
                      "strokeWidth": 1,
                      "fill": "#fff",
                      "style": {
                        "visibility": "hidden"
                      }
                    }
                  }
                }
              },
              "items": [
                {
                  "group": "top",
                  "id": "14018021-cdd3-4b69-9d20-d80402cecd02"
                },
                {
                  "group": "right",
                  "id": "d3a25149-5a7f-44aa-922f-b324230f6ec8"
                },
                {
                  "group": "bottom",
                  "id": "9f9c2a49-44b1-4192-8aee-b60fe5e1523b"
                },
                {
                  "group": "left",
                  "id": "36f7dcb0-9ee8-4527-b10f-85725745f27f"
                }
              ]
            },
            "id": "afa88889-f448-4b87-b2d7-c32a30e0b31b",
            "zIndex": 12,
            "data": {
              "type": "tm.Store",
              "name": "Lee web app config",
              "description": "Archivo de la configuración leído desde el disco",
              "outOfScope": false,
              "isTrustBoundary": false,
              "reasonOutOfScope": "",
              "hasOpenThreats": false,
              "isALog": false,
              "isEncrypted": false,
              "isSigned": false,
              "storesCredentials": false,
              "storesInventory": false,
              "threats": []
            }
          },
          {
            "position": {
              "x": 540,
              "y": 300
            },
            "size": {
              "width": 120,
              "height": 60
            },
            "attrs": {
              "text": {
                "text": "BD"
              },
              "topLine": {
                "stroke": "red",
                "strokeWidth": 2.5,
                "strokeDasharray": null
              },
              "bottomLine": {
                "stroke": "red",
                "strokeWidth": 2.5,
                "strokeDasharray": null
              }
            },
            "visible": true,
            "shape": "store",
            "ports": {
              "groups": {
                "top": {
                  "position": "top",
                  "attrs": {
                    "circle": {
                      "r": 4,
                      "magnet": true,
                      "stroke": "#5F95FF",
                      "strokeWidth": 1,
                      "fill": "#fff",
                      "style": {
                        "visibility": "hidden"
                      }
                    }
                  }
                },
                "right": {
                  "position": "right",
                  "attrs": {
                    "circle": {
                      "r": 4,
                      "magnet": true,
                      "stroke": "#5F95FF",
                      "strokeWidth": 1,
                      "fill": "#fff",
                      "style": {
                        "visibility": "hidden"
                      }
                    }
                  }
                },
                "bottom": {
                  "position": "bottom",
                  "attrs": {
                    "circle": {
                      "r": 4,
                      "magnet": true,
                      "stroke": "#5F95FF",
                      "strokeWidth": 1,
                      "fill": "#fff",
                      "style": {
                        "visibility": "hidden"
                      }
                    }
                  }
                },
                "left": {
                  "position": "left",
                  "attrs": {
                    "circle": {
                      "r": 4,
                      "magnet": true,
                      "stroke": "#5F95FF",
                      "strokeWidth": 1,
                      "fill": "#fff",
                      "style": {
                        "visibility": "hidden"
                      }
                    }
                  }
                }
              },
              "items": [
                {
                  "group": "top",
                  "id": "14018021-cdd3-4b69-9d20-d80402cecd02"
                },
                {
                  "group": "right",
                  "id": "d3a25149-5a7f-44aa-922f-b324230f6ec8"
                },
                {
                  "group": "bottom",
                  "id": "9f9c2a49-44b1-4192-8aee-b60fe5e1523b"
                },
                {
                  "group": "left",
                  "id": "36f7dcb0-9ee8-4527-b10f-85725745f27f"
                }
              ]
            },
            "id": "856ad909-17c3-43d5-b7c5-aa56580c87d7",
            "zIndex": 13,
            "data": {
              "type": "tm.Store",
              "name": "BD",
              "description": "El servidor de la base de datos sera MYSQL y se ejecutara en un servidor linux. este servidor sera reforzado segun el estandar de proteccion de servidores de la universodd. esto incluira la instalacion de los ultimos parches de seguridad del sistema operativo y de las aplicaciones",
              "outOfScope": false,
              "isTrustBoundary": false,
              "reasonOutOfScope": "",
              "hasOpenThreats": true,
              "isALog": false,
              "isEncrypted": false,
              "isSigned": false,
              "storesCredentials": false,
              "storesInventory": false,
              "threats": [
                {
                  "id": "46101ed2-56aa-42ea-b5a8-2c598c4f838a",
                  "title": "acceso no autorizado",
                  "status": "Mitigated",
                  "severity": "Medium",
                  "type": "Information disclosure",
                  "description": "un atacante podria enviar una consulta de bd",
                  "mitigation": "requerir que todas las consultas sean autenticadas",
                  "modelType": "STRIDE",
                  "new": false,
                  "number": 12,
                  "score": ""
                },
                {
                  "id": "d9b7f98f-09a8-4fc2-b743-353a2600a504",
                  "title": "robo de credenciales",
                  "status": "Open",
                  "severity": "Medium",
                  "type": "Information disclosure",
                  "description": "un atacante podria obtener las credenciales de la base de datos y utilizarlas para realizar consultas no autorizadas",
                  "mitigation": "utilize un firewall para restringir el acceso a la base de datos unicamente a la direccion ip del trabajador en segundo plano",
                  "modelType": "STRIDE",
                  "new": false,
                  "number": 13,
                  "score": "2"
                }
              ],
              "threatFrequency": {
                "tampering": 0,
                "repudiation": 0,
                "informationDisclosure": 2,
                "denialOfService": 0
              }
            },
            "tools": {
              "items": [
                "boundary",
                "button-remove",
                "boundary",
                "button-remove"
              ],
              "name": null
            }
          }
        ],
        "description": "a"
      },
      {
        "id": 2,
        "title": "Nuevo diagrama STRIDE",
        "diagramType": "STRIDE",
        "placeholder": "Descripción de nuevo diagrama STRIDE",
        "thumbnail": "./public/content/images/thumbnail.stride.jpg",
        "version": "2.6.0",
        "cells": []
      }
    ],
    "diagramTop": 3,
    "reviewer": "Guillermo Vera ",
    "threatTop": 13
  }
}